vespene/__main__.py
vespene-0.1.0.dist-info/AUTHORS
vespene-0.1.0.dist-info/METADATA
vespene-0.1.0.dist-info/WHEEL
vespene-0.1.0.dist-info/entry_points.txt
vespene-0.1.0.dist-info/pbr.json
vespene-0.1.0.dist-info/top_level.txt
vespene-0.1.0.dist-info/RECORD
